TransparentViewer.py
ZundamonAIStreamer.py
ZundamonAIStreamerManager.py
ZundamonAIStreamerUI.py
__init__.py
zundamonai_streamer-3.0.0.dist-info/LICENSE
zundamonai_streamer-3.0.0.dist-info/LICENSE_ffmpeg
zundamonai_streamer-3.0.0.dist-info/METADATA
zundamonai_streamer-3.0.0.dist-info/WHEEL
zundamonai_streamer-3.0.0.dist-info/top_level.txt
zundamonai_streamer-3.0.0.dist-info/RECORD
