Metadata-Version: 2.1
Name: zundamonai-streamer
Version: 3.0.0
Summary: Zundamon with ChatGPT brain answers aloud YouTube chat messages.
Home-page: https://github.com/GeneralYadoc/ChatAIStreamer
Author: General Yadoc
Author-email: 133023047+GeneralYadoc@users.noreply.github.com
License: MIT
Classifier: Development Status :: 4 - Beta
Classifier: Programming Language :: Python
Classifier: Programming Language :: Python :: 3.7
Classifier: Programming Language :: Python :: 3.8
Classifier: Programming Language :: Python :: 3.9
Classifier: License :: OSI Approved :: MIT License
License-File: LICENSE
License-File: LICENSE_ffmpeg
Requires-Dist: chatai-streamer (==2.0.3)
Requires-Dist: PyYAML (==6.0)
Requires-Dist: deep-translator (==1.11.1)
Requires-Dist: requests (==2.31.0)
Requires-Dist: pydub (==0.25.1)
